[[{"temperature": 20.4}, {"deviceName": "AM107-39", "devEUI": "24e124128c011464", "room": "E209", "floor": 2, "Building": "E"}], [{"temperature": 20.4}, {"deviceName": "AM107-39", "devEUI": "24e124128c011464", "room": "E209", "floor": 2, "Building": "E"}], [{"temperature": 20.3}, {"deviceName": "AM107-39", "devEUI": "24e124128c011464", "room": "E209", "floor": 2, "Building": "E"}], [{"temperature": 20.3}, {"deviceName": "AM107-39", "devEUI": "24e124128c011464", "room": "E209", "floor": 2, "Building": "E"}], [{"temperature": 20.3}, {"deviceName": "AM107-39", "devEUI": "24e124128c011464", "room": "E209", "floor": 2, "Building": "E"}], [{"temperature": 20.2}, {"deviceName": "AM107-39", "devEUI": "24e124128c011464", "room": "E209", "floor": 2, "Building": "E"}], [{"temperature": 20.2}, {"deviceName": "AM107-39", "devEUI": "24e124128c011464", "room": "E209", "floor": 2, "Building": "E"}], [{"temperature": 20.1}, {"deviceName": "AM107-39", "devEUI": "24e124128c011464", "room": "E209", "floor": 2, "Building": "E"}], [{"temperature": 20.1}, {"deviceName": "AM107-39", "devEUI": "24e124128c011464", "room": "E209", "floor": 2, "Building": "E"}], [{"temperature": 19.9}, {"deviceName": "AM107-39", "devEUI": "24e124128c011464", "room": "E209", "floor": 2, "Building": "E"}], [{"temperature": 19.9}, {"deviceName": "AM107-39", "devEUI": "24e124128c011464", "room": "E209", "floor": 2, "Building": "E"}], [{"temperature": 19.9}, {"deviceName": "AM107-39", "devEUI": "24e124128c011464", "room": "E209", "floor": 2, "Building": "E"}], [{"humidity": 39.5}, {"deviceName": "AM107-39", "devEUI": "24e124128c011464", "room": "E209", "floor": 2, "Building": "E"}], [{"humidity": 39.5}, {"deviceName": "AM107-39", "devEUI": "24e124128c011464", "room": "E209", "floor": 2, "Building": "E"}], [{"humidity": 39.5}, {"deviceName": "AM107-39", "devEUI": "24e124128c011464", "room": "E209", "floor": 2, "Building": "E"}], [{"humidity": 39.5}, {"deviceName": "AM107-39", "devEUI": "24e124128c011464", "room": "E209", "floor": 2, "Building": "E"}], [{"humidity": 39.5}, {"deviceName": "AM107-39", "devEUI": "24e124128c011464", "room": "E209", "floor": 2, "Building": "E"}], [{"humidity": 39.5}, {"deviceName": "AM107-39", "devEUI": "24e124128c011464", "room": "E209", "floor": 2, "Building": "E"}], [{"humidity": 39.5}, {"deviceName": "AM107-39", "devEUI": "24e124128c011464", "room": "E209", "floor": 2, "Building": "E"}], [{"humidity": 39.5}, {"deviceName": "AM107-39", "devEUI": "24e124128c011464", "room": "E209", "floor": 2, "Building": "E"}], [{"humidity": 39.5}, {"deviceName": "AM107-39", "devEUI": "24e124128c011464", "room": "E209", "floor": 2, "Building": "E"}], [{"humidity": 39.5}, {"deviceName": "AM107-39", "devEUI": "24e124128c011464", "room": "E209", "floor": 2, "Building": "E"}], [{"humidity": 39.5}, {"deviceName": "AM107-39", "devEUI": "24e124128c011464", "room": "E209", "floor": 2, "Building": "E"}]]