[[{"temperature": 21.3, "co2": 1216}, {"deviceName": "AM107-26", "devEUI": "24e124128c017035", "room": "E003", "floor": 0, "Building": "E"}], [{"temperature": 21.4, "co2": 1326}, {"deviceName": "AM107-26", "devEUI": "24e124128c017035", "room": "E003", "floor": 0, "Building": "E"}], [{"temperature": 21.5, "co2": 1397}, {"deviceName": "AM107-26", "devEUI": "24e124128c017035", "room": "E003", "floor": 0, "Building": "E"}], [{"temperature": 21.6, "activity": 150, "co2": 1457}, {"deviceName": "AM107-26", "devEUI": "24e124128c017035", "room": "E003", "floor": 0, "Building": "E"}], [{"temperature": 21.6, "co2": 1296}, {"deviceName": "AM107-26", "devEUI": "24e124128c017035", "room": "E003", "floor": 0, "Building": "E"}]]