[[{"humidity": 56, "activity": 0, "co2": 429}, {"deviceName": "AM107-51", "devEUI": "24e124128c012168", "room": "amphi1", "floor": 0, "Building": "A"}], [{"humidity": 56, "activity": 0, "co2": 429}, {"deviceName": "AM107-51", "devEUI": "24e124128c012168", "room": "amphi1", "floor": 0, "Building": "A"}], [{"humidity": 56, "activity": 0, "co2": 431}, {"deviceName": "AM107-51", "devEUI": "24e124128c012168", "room": "amphi1", "floor": 0, "Building": "A"}], [{"humidity": 55, "activity": 0, "co2": 422}, {"deviceName": "AM107-51", "devEUI": "24e124128c012168", "room": "amphi1", "floor": 0, "Building": "A"}], [{"humidity": 55, "activity": 0, "co2": 422}, {"deviceName": "AM107-51", "devEUI": "24e124128c012168", "room": "amphi1", "floor": 0, "Building": "A"}], [{"humidity": 55, "activity": 0, "co2": 422}, {"deviceName": "AM107-51", "devEUI": "24e124128c012168", "room": "amphi1", "floor": 0, "Building": "A"}], [{"humidity": 54.5, "activity": 0, "co2": 431}, {"deviceName": "AM107-51", "devEUI": "24e124128c012168", "room": "amphi1", "floor": 0, "Building": "A"}], [{"humidity": 54.5, "activity": 0, "co2": 431}, {"deviceName": "AM107-51", "devEUI": "24e124128c012168", "room": "amphi1", "floor": 0, "Building": "A"}], [{"humidity": 54.5, "activity": 0, "co2": 431}, {"deviceName": "AM107-51", "devEUI": "24e124128c012168", "room": "amphi1", "floor": 0, "Building": "A"}], [{"humidity": 54, "activity": 0, "co2": 431}, {"deviceName": "AM107-51", "devEUI": "24e124128c012168", "room": "amphi1", "floor": 0, "Building": "A"}], [{"humidity": 54, "activity": 0, "co2": 432}, {"deviceName": "AM107-51", "devEUI": "24e124128c012168", "room": "amphi1", "floor": 0, "Building": "A"}], [{"humidity": 53.5, "activity": 0, "co2": 427}, {"deviceName": "AM107-51", "devEUI": "24e124128c012168", "room": "amphi1", "floor": 0, "Building": "A"}], [{"humidity": 53.5, "activity": 0, "co2": 431}, {"deviceName": "AM107-51", "devEUI": "24e124128c012168", "room": "amphi1", "floor": 0, "Building": "A"}], [{"humidity": 52, "activity": 0, "co2": 429}, {"deviceName": "AM107-51", "devEUI": "24e124128c012168", "room": "amphi1", "floor": 0, "Building": "A"}], [{"humidity": 52, "activity": 0, "co2": 429}, {"deviceName": "AM107-51", "devEUI": "24e124128c012168", "room": "amphi1", "floor": 0, "Building": "A"}], [{"humidity": 52, "activity": 0, "co2": 429}, {"deviceName": "AM107-51", "devEUI": "24e124128c012168", "room": "amphi1", "floor": 0, "Building": "A"}], [{"humidity": 52, "activity": 0, "co2": 434}, {"deviceName": "AM107-51", "devEUI": "24e124128c012168", "room": "amphi1", "floor": 0, "Building": "A"}], [{"humidity": 52, "activity": 0, "co2": 434}, {"deviceName": "AM107-51", "devEUI": "24e124128c012168", "room": "amphi1", "floor": 0, "Building": "A"}], [{"temperature": 17.8, "humidity": 51.5, "activity": 0, "co2": 430}, {"deviceName": "AM107-51", "devEUI": "24e124128c012168", "room": "amphi1", "floor": 0, "Building": "A"}], [{"temperature": 17.7, "humidity": 51.5, "activity": 0, "co2": 432}, {"deviceName": "AM107-51", "devEUI": "24e124128c012168", "room": "amphi1", "floor": 0, "Building": "A"}], [{"temperature": 17.7, "humidity": 51.5, "activity": 0, "co2": 432}, {"deviceName": "AM107-51", "devEUI": "24e124128c012168", "room": "amphi1", "floor": 0, "Building": "A"}], [{"temperature": 17.7, "humidity": 51.5, "activity": 0, "co2": 432}, {"deviceName": "AM107-51", "devEUI": "24e124128c012168", "room": "amphi1", "floor": 0, "Building": "A"}], [{"temperature": 17.7, "humidity": 51.5, "activity": 0, "co2": 429}, {"deviceName": "AM107-51", "devEUI": "24e124128c012168", "room": "amphi1", "floor": 0, "Building": "A"}], [{"temperature": 17.7, "humidity": 51.5, "activity": 0, "co2": 429}, {"deviceName": "AM107-51", "devEUI": "24e124128c012168", "room": "amphi1", "floor": 0, "Building": "A"}], [{"temperature": 17.7, "humidity": 51.5, "activity": 0, "co2": 429}, {"deviceName": "AM107-51", "devEUI": "24e124128c012168", "room": "amphi1", "floor": 0, "Building": "A"}], [{"temperature": 17.6, "humidity": 51, "activity": 0, "co2": 429}, {"deviceName": "AM107-51", "devEUI": "24e124128c012168", "room": "amphi1", "floor": 0, "Building": "A"}], [{"temperature": 17.6, "humidity": 51, "activity": 0, "co2": 429}, {"deviceName": "AM107-51", "devEUI": "24e124128c012168", "room": "amphi1", "floor": 0, "Building": "A"}], [{"temperature": 17.6, "humidity": 50.5, "activity": 0, "co2": 425}, {"deviceName": "AM107-51", "devEUI": "24e124128c012168", "room": "amphi1", "floor": 0, "Building": "A"}], [{"temperature": 17.6, "humidity": 50.5, "activity": 0, "co2": 427}, {"deviceName": "AM107-51", "devEUI": "24e124128c012168", "room": "amphi1", "floor": 0, "Building": "A"}], [{"temperature": 17.6, "humidity": 50.5, "activity": 0, "co2": 427}, {"deviceName": "AM107-51", "devEUI": "24e124128c012168", "room": "amphi1", "floor": 0, "Building": "A"}], [{"temperature": 16, "humidity": 45.5, "activity": 0, "co2": 423}, {"deviceName": "AM107-51", "devEUI": "24e124128c012168", "room": "amphi1", "floor": 0, "Building": "A"}], [{"temperature": 16, "humidity": 45.5, "activity": 0, "co2": 423}, {"deviceName": "AM107-51", "devEUI": "24e124128c012168", "room": "amphi1", "floor": 0, "Building": "A"}], [{"temperature": 16, "humidity": 45.5, "activity": 0, "co2": 423}, {"deviceName": "AM107-51", "devEUI": "24e124128c012168", "room": "amphi1", "floor": 0, "Building": "A"}], [{"temperature": 16, "humidity": 45.5, "activity": 0, "co2": 423}, {"deviceName": "AM107-51", "devEUI": "24e124128c012168", "room": "amphi1", "floor": 0, "Building": "A"}], [{"temperature": 16, "humidity": 45.5, "activity": 0, "co2": 423}, {"deviceName": "AM107-51", "devEUI": "24e124128c012168", "room": "amphi1", "floor": 0, "Building": "A"}], [{"temperature": 16, "humidity": 45.5, "activity": 0, "co2": 423}, {"deviceName": "AM107-51", "devEUI": "24e124128c012168", "room": "amphi1", "floor": 0, "Building": "A"}], [{"temperature": 16, "humidity": 45.5, "activity": 0, "co2": 423}, {"deviceName": "AM107-51", "devEUI": "24e124128c012168", "room": "amphi1", "floor": 0, "Building": "A"}], [{"temperature": 15.9, "humidity": 46, "activity": 0, "co2": 425}, {"deviceName": "AM107-51", "devEUI": "24e124128c012168", "room": "amphi1", "floor": 0, "Building": "A"}], [{"temperature": 15.9, "humidity": 46.5, "co2": 421, "pressure": 991.7}, {"deviceName": "AM107-51", "devEUI": "24e124128c012168", "room": "amphi1", "floor": 0, "Building": "A"}], [{"temperature": 15.9, "humidity": 47, "co2": 425, "pressure": 990.9}, {"deviceName": "AM107-51", "devEUI": "24e124128c012168", "room": "amphi1", "floor": 0, "Building": "A"}], [{"temperature": 16, "humidity": 47, "co2": 422, "pressure": 990.8}, {"deviceName": "AM107-51", "devEUI": "24e124128c012168", "room": "amphi1", "floor": 0, "Building": "A"}], [{"temperature": 16, "humidity": 47.5, "co2": 427, "pressure": 990.7}, {"deviceName": "AM107-51", "devEUI": "24e124128c012168", "room": "amphi1", "floor": 0, "Building": "A"}]]